nerdle/__init__.py
nerdle/__main__.py
nerdle/cli.py
nerdle/controllers.py
nerdle/exceptions.py
nerdle/factory.py
nerdle/histogram.py
nerdle/scoring.py
nerdle/simulation.py
nerdle/solver.py
nerdle/view_models.py
nerdle/views.py
nerdle/words.py
nerdle/dictionaries/dictionary-answers-official.json
nerdle/dictionaries/dictionary-answers.json
nerdle/dictionaries/dictionary-full-official.json
nerdle/dictionaries/dictionary-full.json
nerdle-0.0.2.dist-info/LICENSE
nerdle-0.0.2.dist-info/METADATA
nerdle-0.0.2.dist-info/WHEEL
nerdle-0.0.2.dist-info/entry_points.txt
nerdle-0.0.2.dist-info/top_level.txt
nerdle-0.0.2.dist-info/RECORD
