Metadata-Version: 2.1
Name: nerdle
Version: 0.0.2
Summary: nerdle: A nerds approach to playing Wordle
Home-page: https://github.com/CatchemAl/Nerdle
Author: Alex Cross
Author-email: AlexJCross90@gmail.com
License: UNKNOWN
Project-URL: Bug Tracker, https://github.com/CatchemAl/Nerdle/issues
Platform: UNKNOWN
Classifier: Programming Language :: Python :: 3
Classifier: License :: OSI Approved :: MIT License
Classifier: Operating System :: OS Independent
Requires-Python: >=3.8
License-File: LICENSE
Requires-Dist: numba
Requires-Dist: numpy
Requires-Dist: colorama
Provides-Extra: dev
Requires-Dist: black ; extra == 'dev'
Requires-Dist: flake8 ; extra == 'dev'
Requires-Dist: isort ; extra == 'dev'
Requires-Dist: mypy ; extra == 'dev'
Requires-Dist: pytest-cov ; extra == 'dev'
Requires-Dist: tox ; extra == 'dev'
